README.md
setup.py
setup37.py
apalis/__init__.py
apalis/core.py
apalis/plasma_handler.py
apalis/shared.py
apalis/tokens.py
apalis.egg-info/PKG-INFO
apalis.egg-info/SOURCES.txt
apalis.egg-info/dependency_links.txt
apalis.egg-info/requires.txt
apalis.egg-info/top_level.txt
apalis/multiprocessing/__init__.py
apalis/multiprocessing/clinic36.py
apalis/multiprocessing/clinic37.py
apalis/multiprocessing/cpp.py
apalis/multiprocessing/posixshmem.c
apalis/multiprocessing/shared_memory.py