Metadata-Version: 2.1
Name: apalis
Version: 0.1.0.8
Summary: A parallel computing library.
Home-page: https://github.com/danielalcalde/apalis
Author: Daniel Alcalde Puente
Author-email: daniel.alcaldepuente@rub.de
License: MIT
Platform: UNKNOWN
Classifier: Programming Language :: Python :: 3
Classifier: License :: OSI Approved :: MIT License
Requires-Python: >=3.8
